{
  "$schema": "http://json-schema.org/draft-07/schema#",
  "$id": "https://apps-script-studio.com/schemas/nodes/action.iterable.get_record.schema.json",
  "title": "Iterable - Get Record",
  "description": "Get Record in Iterable",
  "type": "object",
  "required": [
    "id",
    "type",
    "position",
    "parameters"
  ],
  "properties": {
    "id": {
      "type": "string",
      "pattern": "^[a-zA-Z0-9_-]+$",
      "description": "Unique identifier for the node"
    },
    "type": {
      "type": "string",
      "const": "action.iterable.get_record",
      "description": "Node type identifier"
    },
    "position": {
      "type": "object",
      "properties": {
        "x": {
          "type": "number"
        },
        "y": {
          "type": "number"
        }
      },
      "required": [
        "x",
        "y"
      ],
      "additionalProperties": false
    },
    "parameters": {
      "type": "object",
      "properties": {
        "data": {
          "description": "Data object",
          "type": "object",
          "additionalProperties": true
        }
      },
      "required": [],
      "additionalProperties": false
    },
    "metadata": {
      "type": "object",
      "properties": {
        "label": {
          "type": "string"
        },
        "description": {
          "type": "string"
        },
        "category": {
          "type": "string",
          "const": "Marketing"
        },
        "appName": {
          "type": "string",
          "const": "Iterable"
        },
        "requiredScopes": {
          "type": "array",
          "items": {
            "type": "string"
          },
          "default": []
        }
      },
      "additionalProperties": false
    }
  },
  "additionalProperties": false
}